{
  "scenario_id": "invalid-truth-path",
  "title": "Invalid direct truth path",
  "valid": false,
  "start_artifact": "intake.packet.json",
  "used_gates": [],
  "allowed_conversions": [],
  "review_artifacts": [],
  "gate_artifacts": [],
  "bundle_manifest": null,
  "forbidden_alternative_paths": [
    "registry truth mutation"
  ],
  "checks": [
    {
      "type": "convert_error",
      "input": "intake.packet.json",
      "to": "registry-truth",
      "code": "conversion_forbidden_target"
    }
  ]
}
